{
	"name": "DS_PARQUET_CSV_TGT",
	"properties": {
		"linkedServiceName": {
			"referenceName": "LS_PARQUET_CSV_TGT",
			"type": "LinkedServiceReference"
		},
		"annotations": [],
		"type": "Parquet",
		"typeProperties": {
			"location": {
				"type": "AzureBlobFSLocation",
				"folderPath": {
					"value": "@concat('excel/',\nformatDateTime(utcNow(),'yyyy'), '/',\nformatDateTime(utcNow(),'MM'), '/',\nformatDateTime(utcNow(),'dd')\n)",
					"type": "Expression"
				}
			},
			"compressionCodec": "snappy"
		},
		"schema": []
	}
}